{"id": 1244, "density": 0.01172425, "max_act": 6.8046875, "hist": {"edges": [0.01, 0.0133, 0.0178, 0.0237, 0.0316, 0.0422, 0.0562, 0.075, 0.1, 0.1334, 0.1778, 0.2371, 0.3162, 0.4217, 0.5623, 0.7499, 1.0, 1.3335, 1.7783, 2.3714, 3.1623, 4.217, 5.6234, 7.4989, 10.0, 13.3352, 17.7828, 23.7137, 31.6228, 42.1697, 56.2341, 74.9894, 100.0], "counts": [0, 0, 0, 0, 0, 0, 0, 0, 0, 0, 15, 328, 1677, 6012, 9122, 8503, 7129, 5819, 2843, 1981, 1443, 1730, 295, 0, 0, 0, 0, 0, 0, 0, 0, 0]}, "logit_lens": {"promoted": [["pping", 0.271], [" hugged", 0.263], [" continued", 0.237], [" goodbye", 0.235], ["erly", 0.234], [" looking", 0.229], ["llie", 0.228], [" walking", 0.227], [" day", 0.223], ["ek", 0.222]], "suppressed": [[" tag", 0.292], ["ber", 0.266], ["ain", 0.26], ["iest", 0.259], [" she", 0.233], ["ier", 0.232], [" window", 0.229], ["ery", 0.221], [" ear", 0.22], ["ay", 0.219]]}, "examples": [{"tokens": ["\n", "\"", "Y", "e", "a", "h", ",", " she", " is", "!\"", " Sam", " says", ".", " \"", "She", " doesn", "'t", " let", " us", " have", " fun", "!\"", "\n", "\n", "They", " sit", " on", " their", " bed", " and", " look", " at", " their"], "acts": [0.0, 0.0, 0.0, 0.0, 0.0, 0.0, 0.0, 0.0, 0.0, 0.0, 0.0, 0.0, 0.0, 0.0, 1.3256, 0.0, 0.0, 0.0, 0.0, 0.0, 0.0, 0.0, 0.0, 0.0, 6.8049, 0.0, 0.0, 0.0, 0.0, 0.0, 0.0, 0.0, 0.0], "max_pos": 24, "max_act": 6.8047}, {"tokens": [" Tom", " back", " and", " says", ",", " \"", "I", "'m", " sorry", ",", " Tom", ",", " I", "'m", " a", " bad", " sister", ".", " I", " love", " you", ".\"", "\n", "\n", "They", " wip", "e", " their", " tears", " and", " smile", ".", " They"], "acts": [0.0, 0.0, 0.0, 0.0, 0.0, 0.0, 0.0, 0.0, 0.0, 0.0, 0.0, 0.0, 0.0, 0.0, 0.0, 0.0, 0.0, 0.0, 0.0, 0.0, 0.0, 0.0, 0.0, 0.0, 6.7703, 1.5854, 0.0, 0.0, 0.0, 0.0, 0.0, 0.0, 1.6218], "max_pos": 24, "max_act": 6.7695}, {"tokens": [" can", " have", " the", " red", " block", ".", " I", " don", "'t", " care", ".\"", "\n", "\n", "They", " smiled", " at", " each", " other", ".", " They", " hugged", "."], "acts": [0.0, 0.0, 0.0, 0.0, 0.0, 0.0, 0.0, 0.0, 0.0, 0.0, 0.0, 0.0, 0.0, 6.7235, 0.0, 0.0, 0.0, 0.0, 0.0, 1.1096, 0.0, 0.0], "max_pos": 13, "max_act": 6.7227}, {"tokens": ["!\"", " Ben", " says", ".", " \"", "And", " the", " cheese", " is", " tight", " and", " stick", "y", ".", " I", " can", "'t", " sw", "all", "ow", " it", ".\"", "\n", "\n", "They", " sp", "it", " out", " the", " salad", " and", " make", " faces"], "acts": [0.0, 0.0, 0.0, 0.0, 0.0, 0.0, 0.0, 0.0, 0.0, 0.0, 0.0, 0.0, 0.0, 0.0, 0.0, 0.0, 0.0, 0.0, 0.0, 0.0, 0.0, 0.0, 0.0, 0.0, 6.7081, 0.0, 0.0, 0.0, 0.0, 0.0, 0.0, 0.0, 0.0], "max_pos": 24, "max_act": 6.707}, {"tokens": [" won", "'t", "!\"", " Tom", " said", ",", " making", " the", " king", " ride", " his", " horse", ".", " \"", "I", " will", " stop", " you", " with", " my", " sword", "!\"", "\n", "\n", "They", " pretended", " to", " fight", " with", " the", " toys", ",", " making"], "acts": [0.0, 0.0, 0.0, 0.0, 0.0, 0.0, 0.5808, 0.0, 0.0, 0.0, 0.0, 0.0, 0.0, 0.0, 0.0, 0.0, 0.0, 0.0, 0.0, 0.0, 0.0, 0.0, 0.0, 0.0, 6.6553, 0.0, 0.0, 0.0, 0.0, 0.0, 0.0, 0.0, 0.0], "max_pos": 24, "max_act": 6.6562}, {"tokens": ["I", " won", "'t", " be", " careless", ",", " Mommy", ".", " I", " promise", "!\"", " Lily", " said", ".", "\n", "\n", "They", " went", " outside", " and", " found", " lots", " of", " rocks", "."], "acts": [0.0, 0.0, 0.0, 0.0, 0.0, 0.0, 0.0, 0.0, 0.0, 0.0, 0.0, 0.0, 0.0, 0.0, 0.0, 0.0, 6.6499, 0.0, 0.0, 0.0, 0.0, 0.0, 0.0, 0.0, 0.0], "max_pos": 16, "max_act": 6.6484}, {"tokens": [",\"", " Sam", " says", ".", " He", " pushes", " Tim", "'s", " block", " away", ".", " \"", "I", " want", " to", " add", " my", " block", " to", " your", " block", ".\"", "\n", "\n", "They", " both", " try", " to", " add", " their", " blocks", " to", " each"], "acts": [0.0, 0.0, 0.0, 0.0, 0.7661, 1.2629, 0.0, 0.0, 0.0, 0.0, 0.0, 0.0, 0.0, 0.0, 0.0, 0.0, 0.0, 0.0, 0.0, 0.0, 0.0, 0.0, 0.0, 0.0, 6.5467, 0.6228, 0.0, 0.8024, 0.0, 0.0, 0.0, 0.0, 0.0], "max_pos": 24, "max_act": 6.5469}, {"tokens": [" necklace", " from", " Lily", ".", " \"", "It", " is", " mine", ".", " You", " can", " have", " something", " else", ".\"", "\n", "\n", "They", " started", " to", " fight", " over", " the", " necklace", ".", " They"], "acts": [0.0, 0.0, 0.0, 0.0, 0.0, 0.0, 0.0, 0.0, 0.0, 0.0, 0.0, 0.0, 0.0, 0.0, 0.0, 0.0, 0.0, 6.4888, 0.0, 0.0, 0.0, 0.0, 0.0, 0.0, 0.0, 1.0372], "max_pos": 17, "max_act": 6.4883}, {"tokens": ["\n", "\"", "I", "'m", " sorry", ",", " Lila", ",\"", " he", " says", ".", " \"", "I", " didn", "'t", " mean", " to", " pull", " your", " dress", ".\"", "\n", "\n", "They", " hug", " and", " say", " sorry", ".", " They", " are", " friends"], "acts": [0.0, 0.0, 0.0, 0.0, 0.0, 0.0, 0.0, 0.0, 0.0, 0.0, 0.0, 0.0, 0.0, 0.0, 0.0, 0.0, 0.0, 0.0, 0.0, 0.0, 0.0, 0.0, 0.0, 6.4492, 0.0, 0.0, 0.0, 0.0, 0.0, 1.9875, 0.0, 0.0], "max_pos": 23, "max_act": 6.4492}, {"tokens": [".\"", "\n", "\n", "\"", "I", " don", "'t", " like", " it", " either", ",\"", " Mia", " says", ".", " \"", "It", " hurts", " my", " to", "ng", "ue", ".\"", "\n", "\n", "They", " throw", " away", " their", " cup", "s", " and", " look", " for"], "acts": [0.0, 0.0, 0.0, 0.0, 0.0, 0.0, 0.0, 0.0, 0.0, 0.0, 0.0, 0.0, 0.0, 0.0, 0.0, 0.0, 0.0, 0.0, 0.0, 0.0, 0.0, 0.0, 0.0, 0.0, 6.4294, 0.0, 0.0, 1.3885, 0.0, 0.0, 0.0, 0.0, 0.0], "max_pos": 24, "max_act": 6.4297}, {"tokens": ["\n", "\"", "I", " don", "'t", " know", ",\"", " Ben", " says", ".", " \"", "Maybe", " it", " is", " not", " good", ".", " Maybe", " it", " is", " old", ".\"", "\n", "\n", "They", " look", " at", " the", " peanut", ".", " It", " is", " attractive"], "acts": [0.0, 0.0, 0.0, 0.0, 0.0, 0.0, 0.0, 0.0, 0.0, 0.0, 0.0, 0.0, 0.0, 0.0, 0.0, 0.0, 0.0, 0.0, 0.0, 0.0, 0.0, 0.0, 0.0, 0.0, 6.431, 0.0, 0.0, 0.0, 0.0, 0.0, 0.0, 0.0, 0.0], "max_pos": 24, "max_act": 6.4297}, {"tokens": [".", " Ben", " holds", " the", " hat", " tight", ".", " He", " says", ",", " \"", "No", ",", " Sam", "!", " It", " is", " mine", "!", " Go", " away", "!\"", "\n", "\n", "They", " start", " to", " fight", ".", " They", " push", " and", " pull"], "acts": [0.0, 0.0, 0.0, 0.0, 0.0, 0.0, 0.0, 0.0, 0.0, 0.0, 0.0, 0.0, 0.0, 0.0, 0.0, 0.0, 0.0, 0.0, 0.0, 0.0, 0.0, 0.0, 0.0, 0.0, 6.4084, 0.0, 0.0, 0.0, 0.0, 2.1396, 0.0, 0.0, 0.0], "max_pos": 24, "max_act": 6.4102}]}