{"id": 862, "density": 0.01946825, "max_act": 9.078125, "hist": {"edges": [0.01, 0.0133, 0.0178, 0.0237, 0.0316, 0.0422, 0.0562, 0.075, 0.1, 0.1334, 0.1778, 0.2371, 0.3162, 0.4217, 0.5623, 0.7499, 1.0, 1.3335, 1.7783, 2.3714, 3.1623, 4.217, 5.6234, 7.4989, 10.0, 13.3352, 17.7828, 23.7137, 31.6228, 42.1697, 56.2341, 74.9894, 100.0], "counts": [0, 0, 0, 0, 0, 0, 0, 0, 0, 2, 20, 216, 2558, 4254, 6049, 5862, 4336, 3744, 6083, 10695, 14331, 12934, 6379, 410, 0, 0, 0, 0, 0, 0, 0, 0]}, "logit_lens": {"promoted": [["Are", 0.457], ["What", 0.442], ["Why", 0.428], ["Can", 0.423], ["Do", 0.413], ["Here", 0.404], ["Where", 0.39], ["Of", 0.367], ["Oh", 0.353], [" Are", 0.341]], "suppressed": [[" go", 0.213], ["a", 0.189], ["e", 0.172], ["re", 0.17], ["on", 0.159], ["ap", 0.157], [" noise", 0.154], [" leave", 0.148], ["l", 0.146], ["at", 0.145]]}, "examples": [{"tokens": ["\n", "\n", "\"", "M", "ail", " for", " us", "?", " W", "ow", "!\""], "acts": [0.0, 0.0, 9.0759, 0.0, 0.0, 0.0, 0.0, 4.2132, 0.0, 0.0, 0.0], "max_pos": 2, "max_act": 9.0781}, {"tokens": ["\n", "\n", "\"", "That", "'s", " so", " cool", ",\"", " said", " Lucy", "."], "acts": [0.0, 0.0, 9.0759, 0.0, 0.0, 0.0, 0.0, 0.0, 0.0, 0.0, 0.0], "max_pos": 2, "max_act": 9.0781}, {"tokens": ["\n", "\n", "\"", "I", " see", " it", "!", " I", " wonder", " what", " animals"], "acts": [0.0, 0.0, 9.0759, 0.0, 0.0, 0.0, 1.7811, 0.0, 0.0, 0.0, 0.0], "max_pos": 2, "max_act": 9.0781}, {"tokens": ["\n", "\n", "\"", "Are", " you", " okay", "?\"", " Timmy", " asked", ".", "\n"], "acts": [0.0, 0.0, 9.0759, 0.0, 0.0, 0.0, 0.0, 0.0, 0.0, 0.0, 0.7362], "max_pos": 2, "max_act": 9.0781}, {"tokens": ["\n", "\n", "\"", "Wow", ",", " look", " at", " these", "!\"", " Ben", " says"], "acts": [0.0, 0.0, 9.0759, 0.0, 0.0, 0.0, 0.0, 0.0, 0.0, 0.0, 0.0], "max_pos": 2, "max_act": 9.0781}, {"tokens": ["\n", "\n", "\"", "Hello", ",", " kids", ",\"", " he", " says", ".", " \""], "acts": [0.0, 0.0, 9.0759, 0.0, 0.0, 0.0, 0.0, 0.0, 0.0, 1.1069, 5.823], "max_pos": 2, "max_act": 9.0781}, {"tokens": ["\n", "\n", "\"", "Can", " I", " play", " with", " you", "?\"", " Max", " asked"], "acts": [0.0, 0.0, 9.0759, 0.0, 0.0, 0.0, 0.0, 0.0, 0.0, 0.0, 0.0], "max_pos": 2, "max_act": 9.0781}, {"tokens": ["\n", "\n", "\"", "No", ",", " Sara", ",", " don", "'t", " touch", " it"], "acts": [0.0, 0.0, 9.0759, 0.0, 0.0, 0.0, 0.0, 0.0, 0.0, 0.0, 0.0], "max_pos": 2, "max_act": 9.0781}, {"tokens": ["\n", "\n", "\"", "I", " want", " a", " cone", " with", " chocolate", " and", " van"], "acts": [0.0, 0.0, 9.0759, 0.0, 0.0, 0.0, 0.0, 0.0, 0.0, 0.0, 0.0], "max_pos": 2, "max_act": 9.0781}, {"tokens": ["\n", "\n", "\"", "It", "'s", " a", " flute", ",\"", " Lily", " said", " soft"], "acts": [0.0, 0.0, 9.0759, 0.0, 0.0, 0.0, 0.0, 0.0, 0.0, 0.0, 0.0], "max_pos": 2, "max_act": 9.0781}, {"tokens": ["\n", "\n", "\"", "Oh", " no", "!", " We", " destroy", "ed", " the", " apple"], "acts": [0.0, 0.0, 9.0759, 0.0, 0.0, 3.9655, 0.0, 0.0, 0.0, 0.0, 0.0], "max_pos": 2, "max_act": 9.0781}, {"tokens": ["\n", "\n", "\"", "Hey", ",", " you", " kids", ",", " get", " away", " from"], "acts": [0.0, 0.0, 9.0759, 0.0, 0.0, 0.0, 0.0, 0.0, 0.0, 0.0, 0.0], "max_pos": 2, "max_act": 9.0781}]}