{"id": 360, "density": 0.00885775, "max_act": 9.546875, "hist": {"edges": [0.01, 0.0133, 0.0178, 0.0237, 0.0316, 0.0422, 0.0562, 0.075, 0.1, 0.1334, 0.1778, 0.2371, 0.3162, 0.4217, 0.5623, 0.7499, 1.0, 1.3335, 1.7783, 2.3714, 3.1623, 4.217, 5.6234, 7.4989, 10.0, 13.3352, 17.7828, 23.7137, 31.6228, 42.1697, 56.2341, 74.9894, 100.0], "counts": [0, 0, 0, 0, 0, 0, 0, 0, 0, 0, 0, 11, 221, 1327, 3369, 4414, 4174, 3732, 3654, 4050, 4287, 3529, 1997, 666, 0, 0, 0, 0, 0, 0, 0, 0]}, "logit_lens": {"promoted": [[" there", 0.306], [" they", 0.262], [" someone", 0.261], [" everyone", 0.251], ["ver", 0.245], [" nobody", 0.231], [" other", 0.228], [" everything", 0.227], [" it", 0.216], [" she", 0.208]], "suppressed": [[" pr", 0.313], [" careful", 0.308], ["ong", 0.305], ["her", 0.301], ["ol", 0.298], ["kin", 0.295], [" pad", 0.291], ["ou", 0.285], [" practiced", 0.268], ["used", 0.267]]}, "examples": [{"tokens": [".", " So", " she", " wanted", " to", " take", " a", " closer", " look", " inside", ".", " \n", "\n", "When", " she", " opened", " the", " door", ",", " R", "u", "by", " saw", " that", " the", " cabin", "et", " was", " filled", " with", " things", " that"], "acts": [0.0, 0.0, 0.0, 0.0, 0.0, 0.0, 0.0, 0.0, 0.0, 0.0, 0.0, 0.0, 0.0, 0.0, 0.0, 0.0, 0.0, 0.0, 0.0, 0.0, 0.0, 0.0, 0.0, 9.5466, 0.0, 0.0, 0.0, 0.0, 0.0, 0.0, 0.0, 2.5446], "max_pos": 23, "max_act": 9.5469}, {"tokens": ["les", " in", " the", " closet", ".", " Then", " one", " day", ",", " she", " smelled", " something", " strange", " coming", " from", " her", " closet", ".", " Jane", " opened", " the", " door", " and", " saw", " that", " the", " once", " spicy", " n", "ood", "les", " were", " now"], "acts": [0.0, 0.0, 0.0, 0.0, 0.0, 0.0, 0.0, 0.0, 0.0, 0.0, 0.0, 0.0, 0.0, 0.0, 0.0, 0.0, 0.0, 0.0, 0.0, 0.0, 0.0, 0.0, 0.0, 0.0, 9.2703, 0.0, 0.0, 0.0, 0.0, 0.0, 0.0, 0.0, 0.0], "max_pos": 24, "max_act": 9.2734}, {"tokens": [" got", " a", " spoon", " and", " started", " to", " write", " in", " the", " rice", ".", " After", " wr", "iting", " for", " a", " few", " minutes", ",", " M", "ag", "g", "ie", " saw", " that", " the", " rice", " had", " got", "ten", " quite", " messy", "."], "acts": [0.0, 0.0, 0.0, 0.0, 0.0, 0.0, 0.0, 0.0, 0.0, 0.0, 0.0, 0.0, 0.0, 0.0, 0.0, 0.0, 0.0, 0.0, 0.0, 0.0, 0.0, 0.0, 0.0, 0.5042, 9.1036, 0.0, 0.0, 0.0, 0.0, 0.0, 0.0, 0.0, 0.0], "max_pos": 24, "max_act": 9.1016}, {"tokens": [" \n", "\n", "The", " little", " girl", " was", " so", " excited", ".", " She", " was", " cooking", " her", " very", " own", " meal", ".", " Her", " mummy", " came", " to", " check", " and", " saw", " that", " the", " little", " girl", " had", " done", " a", " very", " good"], "acts": [0.0, 0.0, 0.0, 0.0, 0.0, 0.0, 0.0, 0.0, 0.0, 0.0, 0.0, 0.0, 0.0, 0.0, 0.0, 0.0, 0.0, 0.0, 0.0, 0.0, 0.0, 0.0, 0.0, 0.0, 9.0818, 0.0, 0.0, 0.0, 0.0, 0.0, 0.0, 0.0, 0.0], "max_pos": 24, "max_act": 9.0781}, {"tokens": [" She", " put", " her", " teddy", " bear", " in", " the", " bin", " too", ".", " But", " then", " she", " saw", " that", " her", " teddy", " bear", "'s", " ear", " was", " not", " fine"], "acts": [0.0, 0.0, 0.0, 0.0, 0.0, 0.0, 0.0, 0.0, 0.0, 0.0, 0.0, 0.0, 0.0, 0.6624, 9.0542, 0.0, 0.0, 0.0, 0.0, 0.0, 0.0, 0.0, 0.0], "max_pos": 14, "max_act": 9.0547}, {"tokens": [" dark", " storm", " came", " and", " all", " the", " plants", " got", " wet", " from", " the", " rain", ".", " When", " morning", " came", ",", " Sarah", " looked", " in", " the", " garden", " and", " saw", " that", " a", " dark", " plant", " was", " missing", ".", " She", " gasped"], "acts": [0.0, 0.0, 0.0, 0.0, 0.0, 0.0, 0.0, 0.0, 0.0, 0.0, 0.0, 0.0, 0.0, 0.0, 0.0, 0.0, 0.7218, 0.0, 0.0, 0.0, 0.0, 0.0, 0.0, 0.0, 9.0013, 0.0, 0.0, 0.0, 0.0, 0.0, 0.0, 0.0, 0.0], "max_pos": 24, "max_act": 9.0}, {"tokens": [" of", " the", " kangaroo", " and", " the", " baby", " on", " her", " notebook", ".", "\n", "\n", "Suddenly", ",", " she", " heard", " a", " noise", ".", " She", " looked", " up", " and", " saw", " that", " the", " baby", " kangaroo", " had", " jumped", " out", " of", " the"], "acts": [0.0, 0.0, 0.0, 0.0, 0.0, 0.0, 0.0, 0.0, 0.0, 0.0, 0.0, 0.0, 0.0, 0.0, 0.0, 0.0, 0.0, 0.0, 0.0, 0.0, 0.0, 0.0, 0.0, 0.0, 8.9455, 0.0, 0.0, 0.0, 0.0, 0.0, 0.0, 0.0, 0.0], "max_pos": 24, "max_act": 8.9453}, {"tokens": [" small", " rocket", " came", " flying", " by", ".", " It", " was", " seen", " from", " a", " very", " far", " away", " place", ".", " When", " it", " came", " close", ",", " every", "body", " saw", " that", " it", " was", " an", " ordinary", " rocket", ".", " But", " there"], "acts": [0.0, 0.0, 0.0, 0.0, 0.0, 0.0, 0.0, 0.0, 0.0, 0.0, 0.0, 0.0, 0.0, 0.0, 0.0, 0.0, 0.0, 0.0, 0.0, 0.0, 0.0, 0.0, 0.0, 0.0, 8.9225, 0.0, 0.0, 0.0, 0.0, 0.0, 0.0, 0.0, 0.0], "max_pos": 24, "max_act": 8.9219}, {"tokens": [" scr", "u", "bb", "ing", ",", " but", " the", " dirt", " didn", "'t", " go", " away", ".", " \n", "\n", "Tom", "'s", " mom", " came", " into", " the", " bathroom", " and", " saw", " that", " the", " trophy", " was", " still", " dirty", ".", " She", " said"], "acts": [0.0, 0.0, 0.0, 0.0, 0.0, 0.0, 0.0, 0.0, 0.0, 0.0, 0.0, 0.0, 0.0, 0.0, 0.0, 0.0, 0.0, 0.0, 0.0, 0.0, 0.0, 0.0, 0.0, 0.0, 8.9095, 0.0, 0.0, 0.0, 0.0, 0.0, 0.0, 0.0, 0.0], "max_pos": 24, "max_act": 8.9062}, {"tokens": [" the", " window", " to", " see", " what", " was", " happening", " all", " around", ".", " \n", "\n", "One", " day", " when", " he", " looked", " out", ",", " the", " king", " saw", " that", " the", " door", " to", " the", " castle", " was", " open", "!"], "acts": [0.0, 0.0, 0.0, 0.0, 3.5414, 0.0, 0.0, 0.0, 0.0, 0.0, 0.0, 0.0, 0.0, 0.0, 0.0, 0.0, 0.0, 0.0, 0.0, 0.0, 0.0, 0.0, 8.9027, 0.0, 0.0, 0.0, 0.0, 0.0, 0.0, 0.0, 0.0], "max_pos": 22, "max_act": 8.9062}, {"tokens": [" ducks", " away", ".", " Daisy", " moved", " closer", " and", " saw", " that", " the", " angry", " duck", " had", " a", " hurt", " hand", "."], "acts": [0.0, 0.0, 0.0, 0.0, 0.0, 0.0, 0.0, 0.0, 8.8658, 0.0, 0.0, 0.0, 0.0, 0.0, 0.0, 0.0, 0.0], "max_pos": 8, "max_act": 8.8672}, {"tokens": [" he", " wanted", " to", " touch", " the", " rainbow", " so", " much", ".", " \n", "\n", "Then", ",", " it", " started", " to", " rain", ".", " The", " bunny", " looked", " up", " and", " saw", " that", " the", " rainbow", " was", " gone", ".", " He", " felt", " even"], "acts": [0.0, 0.0, 0.0, 0.0, 0.0, 0.0, 0.0, 0.0, 0.0, 0.0, 0.0, 0.0, 0.0, 0.0, 0.0, 0.0, 0.0, 0.0, 0.0, 0.0, 0.0, 0.0, 0.0, 0.0, 8.8166, 0.0, 0.0, 0.0, 0.0, 0.0, 0.0, 0.0, 0.0], "max_pos": 24, "max_act": 8.8203}]}