{"id": 903, "density": 0.00965425, "max_act": 6.65234375, "hist": {"edges": [0.01, 0.0133, 0.0178, 0.0237, 0.0316, 0.0422, 0.0562, 0.075, 0.1, 0.1334, 0.1778, 0.2371, 0.3162, 0.4217, 0.5623, 0.7499, 1.0, 1.3335, 1.7783, 2.3714, 3.1623, 4.217, 5.6234, 7.4989, 10.0, 13.3352, 17.7828, 23.7137, 31.6228, 42.1697, 56.2341, 74.9894, 100.0], "counts": [0, 0, 0, 0, 0, 0, 0, 0, 9, 143, 832, 1862, 3035, 4240, 4354, 3914, 3302, 4224, 1692, 423, 2333, 7429, 825, 0, 0, 0, 0, 0, 0, 0, 0, 0]}, "logit_lens": {"promoted": [[" there", 0.242], [" Mommy", 0.206], ["itten", 0.199], [" Sam", 0.179], [" fair", 0.173], [" Mom", 0.166], [" Ben", 0.166], [" two", 0.165], [" Billy", 0.164], [" Jack", 0.164]], "suppressed": [[" enc", 0.331], ["Stop", 0.314], [" sound", 0.312], [" sounds", 0.311], [" scold", 0.301], [" stumbled", 0.3], [" tripped", 0.299], [" pad", 0.289], [" tem", 0.286], [" apolog", 0.286]]}, "examples": [{"tokens": [" he", " had", " not", " tried", " to", " sell", " his", " brother", "'s", " toy", ".", " He", " learned", " that", " sharing", " was", " better", " than", " sell", "ing", ".", "<|endoftext|>", "One", " day", ",", " a", " boy", " named", " Ben", " went", " to", " the", " zoo"], "acts": [0.0, 0.0, 0.0, 0.0, 0.0, 0.0, 0.0, 0.0, 0.0, 0.0, 0.0, 0.0, 0.0, 0.0, 0.0, 0.0, 0.0, 0.0, 0.0, 0.0, 0.0, 0.0, 0.0, 3.7593, 6.6541, 2.5226, 0.0, 0.0, 0.0, 0.0, 0.0, 0.0, 0.0], "max_pos": 24, "max_act": 6.6523}, {"tokens": [" promised", " to", " be", " a", " good", " boy", " from", " then", " on", ".", " He", " never", " li", "ed", " or", " drank", " po", "is", "on", " again", ".", "<|endoftext|>", "One", " day", ",", " a", " curious", " boy", " named", " Ben", " found", " a", " big"], "acts": [0.0, 0.0, 0.0, 0.0, 0.0, 0.0, 0.0, 0.0, 0.0, 0.0, 0.0, 0.0, 0.0, 0.0, 0.0, 0.0, 0.0, 0.0, 0.0, 0.0, 0.0, 0.0, 0.0, 3.9264, 6.5178, 1.9478, 0.0, 0.0, 0.0, 0.0, 0.0, 0.0, 0.0], "max_pos": 24, "max_act": 6.5195}, {"tokens": [",", " the", " bad", " person", " took", " the", " purse", " and", " ran", " away", ".", " The", " lady", " was", " very", " sad", " and", " cried", " a", " lot", ".", "<|endoftext|>", "One", " day", ",", " a", " little", " girl", " named", " Lily", " went", " to", " the"], "acts": [0.0, 0.0, 0.0, 0.0, 0.0, 0.0, 0.0, 0.0, 0.0, 0.0, 0.0, 0.0, 0.0, 0.0, 0.0, 0.0, 0.0, 0.0, 0.0, 0.0, 0.0, 0.0, 0.0, 3.8656, 6.4525, 2.2962, 0.0, 0.0, 0.0, 0.0, 0.0, 0.0, 0.0], "max_pos": 24, "max_act": 6.4531}, {"tokens": [" The", " hot", " air", " balloon", " rem", "ained", " in", " the", " sky", ",", " making", " M", "im", "i", "'s", " building", " nice", " and", " co", "sy", ".", "<|endoftext|>", "One", " morning", ",", " a", " young", " girl", " woke", " up", " from", " her", " bed"], "acts": [0.0, 0.0, 0.0, 0.0, 0.0, 0.0, 0.0, 0.0, 0.0, 0.0, 0.0, 0.0, 0.0, 0.0, 0.0, 0.0, 0.0, 0.0, 0.0, 0.0, 0.0, 0.0, 0.0, 1.6684, 6.4432, 1.998, 0.0, 0.0, 0.0, 0.0, 0.0, 0.0, 0.0], "max_pos": 24, "max_act": 6.4414}, {"tokens": [" the", " warm", "th", " of", " the", " day", ".", " They", " knew", " that", " was", " the", " way", " it", " was", " supp", "o", "sed", " to", " be", ".", "<|endoftext|>", "One", " day", ",", " there", " was", " a", " helpless", " puppy", " called", " Pat", "."], "acts": [0.0, 0.0, 0.0, 0.0, 0.0, 0.0, 0.0, 0.0, 0.0, 0.0, 0.0, 0.0, 0.0, 0.0, 0.0, 0.0, 0.0, 0.0, 0.0, 0.0, 0.0, 0.0, 0.0, 3.9212, 6.3979, 0.0, 0.0, 0.0, 0.0, 0.0, 1.3174, 0.0, 0.0], "max_pos": 24, "max_act": 6.3984}, {"tokens": [" for", " her", " hug", ".", " They", " both", " enjoyed", " the", " sweet", " jam", " together", ",", " and", " soon", ",", " Tom", "'s", " finger", " heal", "ed", ".", "<|endoftext|>", "One", " day", ",", " a", " boy", " went", " to", " visit", " a", " king", "."], "acts": [0.0, 0.0, 0.0, 0.0, 0.0, 0.0, 0.0, 0.0, 0.0, 0.0, 0.0, 0.0, 0.0, 0.0, 0.0, 0.0, 0.0, 0.0, 0.0, 0.0, 0.0, 0.0, 0.0, 3.6185, 6.39, 1.935, 0.0, 0.0, 0.0, 0.0, 0.0, 0.0, 0.0], "max_pos": 24, "max_act": 6.3906}, {"tokens": [" and", " thanked", " him", " for", " playing", ".", " The", " t", "ur", "key", " waved", " and", " smiled", ".", " He", " hoped", " to", " see", " them", " again", ".", "<|endoftext|>", "One", " day", ",", " Lily", " and", " Tom", " went", " to", " the", " park", " with"], "acts": [0.0, 0.0, 0.0, 0.0, 0.0, 0.0, 0.0, 0.0, 0.0, 0.0, 0.0, 0.0, 0.0, 0.0, 0.0, 0.0, 0.0, 0.0, 0.0, 0.0, 0.0, 0.0, 0.0, 3.6167, 6.3882, 0.6934, 0.0, 0.0, 0.0, 0.0, 0.0, 0.0, 0.0], "max_pos": 24, "max_act": 6.3867}, {"tokens": [" and", " had", " so", " much", " fun", ".", " In", " the", " end", ",", " they", " all", " thanked", " Amy", " for", " the", " delicious", " pretend", " fe", "ast", ".", "<|endoftext|>", "One", " day", ",", " a", " little", " girl", " named", " Mia", " went", " to", " a"], "acts": [0.0, 0.0, 0.0, 0.0, 0.0, 0.0, 0.0, 0.0, 0.0, 0.0, 0.0, 0.0, 0.0, 0.0, 0.0, 0.0, 0.0, 0.0, 0.0, 0.0, 0.0, 0.0, 0.0, 3.8152, 6.3638, 2.5048, 0.0, 0.0, 0.0, 0.0, 0.0, 0.0, 0.0], "max_pos": 24, "max_act": 6.3633}, {"tokens": [" At", " the", " end", " of", " the", " day", ",", " the", " hole", " was", " rep", "a", "ired", " and", " they", " all", " had", " a", " fun", " time", ".", "<|endoftext|>", "One", " day", ",", " a", " little", " pengu", "in", " named", " P", "ip", " went"], "acts": [0.0, 0.0, 0.0, 0.0, 0.0, 0.0, 0.0, 0.0, 0.0, 0.0, 0.0, 0.0, 0.0, 0.0, 0.0, 0.0, 0.0, 0.0, 0.0, 0.0, 0.0, 0.0, 0.0, 3.8205, 6.3531, 1.8383, 0.0, 0.0, 0.0, 0.6507, 0.0, 0.0, 0.0], "max_pos": 24, "max_act": 6.3516}, {"tokens": [" car", "ing", ".", " Be", "ing", " kind", " is", " better", " than", " being", " organized", ".", " F", "riend", "s", " are", " more", " important", " than", " things", ".", "<|endoftext|>", "One", " day", ",", " a", " lion", " was", " very", " bored", ".", " He", " had"], "acts": [0.0, 0.0, 0.0, 0.0, 0.0, 0.0, 0.0, 0.0, 0.0, 0.0, 0.0, 0.0, 0.0, 0.0, 0.0, 0.0, 0.0, 0.0, 0.0, 0.0, 0.0, 0.0, 0.0, 3.726, 6.3431, 1.8332, 0.0, 0.0, 0.0, 0.0, 0.0, 0.0, 0.0], "max_pos": 24, "max_act": 6.3438}, {"tokens": [".", " At", " the", " end", " of", " the", " day", ",", " they", " went", " home", " and", " told", " their", " mom", " about", " the", " fun", " they", " had", ".", "<|endoftext|>", "One", " day", ",", " a", " pink", " car", " named", " Sp", "e", "ed", "y"], "acts": [0.0, 0.0, 0.0, 0.0, 0.0, 0.0, 0.0, 0.0, 0.0, 0.0, 0.0, 0.0, 0.0, 0.0, 0.0, 0.0, 0.0, 0.0, 0.0, 0.0, 0.0, 0.0, 0.0, 3.5932, 6.3276, 1.898, 0.0, 0.0, 0.5659, 0.0, 0.0, 0.0, 0.0], "max_pos": 24, "max_act": 6.3281}, {"tokens": [" grateful", " for", " what", " they", " have", " and", " not", " be", " gre", "ed", "y", " for", " what", " they", " don", "'t", ".", "<|endoftext|>", "One", " day", ",", " two", " friends", ",", " Lily", " and", " Ben", ",", " went"], "acts": [0.0, 0.0, 0.0, 0.0, 0.0, 0.0, 0.0, 0.0, 0.0, 0.0, 0.0, 0.0, 0.0, 0.0, 0.0, 0.0, 0.0, 0.0, 0.0, 3.997, 6.3245, 0.0, 1.4997, 1.6863, 0.0, 0.0, 0.0, 0.0, 0.0], "max_pos": 20, "max_act": 6.3242}]}