{"id": 983, "density": 0.02374975, "max_act": 6.77734375, "hist": {"edges": [0.01, 0.0133, 0.0178, 0.0237, 0.0316, 0.0422, 0.0562, 0.075, 0.1, 0.1334, 0.1778, 0.2371, 0.3162, 0.4217, 0.5623, 0.7499, 1.0, 1.3335, 1.7783, 2.3714, 3.1623, 4.217, 5.6234, 7.4989, 10.0, 13.3352, 17.7828, 23.7137, 31.6228, 42.1697, 56.2341, 74.9894, 100.0], "counts": [0, 0, 0, 0, 0, 0, 0, 0, 0, 0, 7, 96, 783, 3237, 8781, 16958, 21870, 19055, 12748, 7301, 3253, 866, 44, 0, 0, 0, 0, 0, 0, 0, 0, 0]}, "logit_lens": {"promoted": [["s", 0.409], ["g", 0.328], ["es", 0.324], ["is", 0.319], ["-", 0.301], ["ies", 0.294], ["ages", 0.289], ["on", 0.282], ["y", 0.276], ["ing", 0.275]], "suppressed": [[" adventur", 0.295], ["imal", 0.288], [" medic", 0.283], ["ident", 0.282], [" mor", 0.282], ["aught", 0.279], ["cod", 0.277], ["ungle", 0.277], ["upid", 0.275], [" sug", 0.268]]}, "examples": [{"tokens": ["\n", "\n", "Anna", " nodded", " and", " smiled", ".", " She", " felt", " better", ".", " She", " loved", " her", " mom", " too", ".", " She", " learned", " to", " be", " more", " careful", " with", " door", "s", " and", " clothes", ".", " She", " still", " liked", " to"], "acts": [0.0, 0.0, 0.0, 0.0, 0.0, 0.0, 0.0, 0.0, 0.0, 0.0, 0.0, 0.0, 0.0, 0.0, 0.0, 0.0, 0.0, 0.0, 0.0, 0.0, 0.0, 0.0, 0.0, 0.0, 6.7769, 1.4255, 0.0, 0.8892, 0.0, 0.0, 0.0, 0.0, 0.0], "max_pos": 24, "max_act": 6.7773}, {"tokens": [" decided", " to", " keep", " spread", "ing", " out", " to", " discover", " new", " things", ".", " They", " explored", " mountain", " top", "s", ",", " swam", " in", " la", "kes", ","], "acts": [0.0, 0.0, 0.0, 0.0, 0.0, 1.507, 0.0, 0.0, 1.4209, 0.0, 0.0, 0.0, 0.0, 6.763, 3.6673, 1.2046, 0.0, 0.0, 0.0, 1.8952, 1.5149, 0.0], "max_pos": 13, "max_act": 6.7617}, {"tokens": [" look", " for", " sign", "s", " of", " animals", ",", " like", " birds", ",", " squirrel", "s", " and", " bugs", ".", "\n", "\n", "One", " day"], "acts": [0.0, 1.235, 3.8326, 0.0, 0.0, 1.8516, 0.0, 0.0, 1.9318, 0.0, 6.5767, 1.2021, 0.0, 0.0, 0.0, 0.0, 0.0, 0.0, 0.0], "max_pos": 10, "max_act": 6.5781}, {"tokens": [" of", " different", " shapes", " and", " colors", ".", " He", " liked", " to", " try", " them", " on", " different", " door", "s", " and", " lo", "cks", ".", " He", " wanted", " to"], "acts": [0.0, 0.0, 0.0, 0.0, 0.0, 0.0, 0.0, 0.0, 0.0, 0.0, 0.0, 0.9723, 1.3136, 6.4731, 0.0, 0.0, 2.3338, 1.2322, 0.0, 0.0, 0.0, 0.0], "max_pos": 13, "max_act": 6.4727}, {"tokens": [" decided", " to", " prep", "are", " a", " special", " pot", "ion", ".", " She", " needed", " some", " special", " ingredients", " like", " frog", " legs", " and", " spider", " we", "b", "s", ".", " She"], "acts": [0.0, 0.0, 0.0, 0.0, 0.0, 0.0, 0.0, 0.0, 0.0, 0.0, 0.0, 0.0, 0.0, 0.0, 0.0, 6.41, 2.7651, 0.0, 5.3964, 0.0, 2.5683, 0.0, 0.0, 0.0], "max_pos": 15, "max_act": 6.4102}, {"tokens": [" She", " said", ",", " \"", "I", "'m", " sorry", ",", " Tom", ".", " I", " hope", " you", " feel", " better", " soon", ".", " N", "ext", " time", ",", " be", " careful", " with", " fork", "s", " and", " ask", " nicely", " if", " you", " want", " to"], "acts": [0.0, 0.0, 0.0, 0.0, 0.0, 0.0, 0.0, 0.0, 0.0, 0.0, 0.0, 0.0, 0.0, 0.0, 0.0, 0.0, 0.0, 0.0, 0.0, 0.0, 0.0, 0.0, 0.0, 0.0, 6.4113, 0.8551, 0.0, 0.0, 0.0, 0.0, 0.0, 0.0, 0.0], "max_pos": 24, "max_act": 6.4102}, {"tokens": [" A", "mer", "ic", "a", ".", " We", " live", " here", ".", " We", " can", " go", " anywhere", " we", " want", " in", " A", "mer", "ic", "a", ".", " We", " can", " see", " mountain", "s", " and", " river", "s", " and", " c", "it", "ies"], "acts": [0.0, 0.0, 0.0, 0.0, 0.0, 0.0, 0.0, 0.0, 0.0, 0.0, 0.0, 0.0, 0.0, 0.0, 0.0, 0.0, 0.0, 0.0, 0.0, 0.0, 0.0, 0.0, 0.0, 0.0, 6.2654, 1.5455, 0.0, 4.4037, 0.0, 0.0, 1.4837, 1.1669, 0.0], "max_pos": 24, "max_act": 6.2656}, {"tokens": [" his", " wallet", ".", " M", "other", " shook", " her", " head", " and", " said", ",", " \"", "We", " don", "'t", " believe", " in", " playing", " with", " wall", "ets", ".", " That", "'s", " silly", ".", " You", " should"], "acts": [0.0, 0.0, 0.0, 0.0, 0.0, 0.0, 0.0, 0.0, 0.0, 0.0, 0.0, 0.0, 0.0, 0.0, 0.0, 0.0, 0.0, 0.0, 0.0, 6.2631, 2.4889, 0.0, 0.0, 0.0, 0.0, 0.0, 0.0, 0.0], "max_pos": 19, "max_act": 6.2617}, {"tokens": [" the", " people", " who", " live", " around", " here", " are", " gentle", " and", " kind", ".\"", " \n", "\n", "A", "bby", " smiled", " and", " said", ",", " \"", "I", " know", " all", " about", " flag", "s", " now", "!\"", " She", " spent", " the", " afternoon", " playing"], "acts": [0.0, 0.0, 0.0, 0.0, 0.0, 0.0, 0.0, 1.3887, 0.0, 0.0, 0.0, 0.0, 0.0, 0.0, 0.0, 0.0, 0.0, 0.0, 0.0, 0.0, 0.0, 0.0, 0.0, 0.0, 6.1613, 1.4714, 0.0, 0.0, 0.0, 0.0, 0.0, 0.0, 0.0], "max_pos": 24, "max_act": 6.1602}, {"tokens": [" wished", " that", " people", " would", " understand", " and", " not", " be", " afraid", " of", " shark", "s", ".", " Tim", " listened", " to", " his", " dad", " and", " promised", " to", " learn", " more", " about", " shark", "s", " so", " that", " he", " wouldn", "'t", " be", " scared"], "acts": [0.0, 0.0, 0.0, 0.0, 0.0, 0.0, 0.0, 0.0, 0.0, 0.0, 5.601, 0.0, 0.0, 0.0, 0.0, 0.0, 0.0, 0.0, 0.0, 0.0, 0.0, 0.0, 0.0, 0.0, 6.1411, 0.0, 0.0, 0.0, 0.0, 0.0, 0.0, 0.0, 0.0], "max_pos": 24, "max_act": 6.1406}, {"tokens": ["\"", "We", "'re", " set", "ting", " up", " a", " net", "work", " of", " wire", "s", ",\"", " her", " friend", " Ben", " said", ".", " He", " was", " feeling", " very", " anxious", " about", " fin", "is", "hing", " the", " job", ".", " \n", "\n", "T"], "acts": [0.0, 0.0, 0.0, 1.0854, 0.0, 0.0, 0.0, 0.0, 0.0, 0.0, 3.0464, 0.0, 0.0, 0.0, 0.0, 0.0, 0.0, 0.0, 0.0, 0.0, 0.0, 0.0, 0.0, 0.0, 6.082, 2.0867, 0.0, 0.0, 0.0, 0.0, 0.0, 0.0, 0.8407], "max_pos": 24, "max_act": 6.082}, {"tokens": [" loved", " the", " feeling", "!", " They", " walked", " along", " the", " shore", " and", " saw", " lots", " of", " se", "ag", "ull", "s", " flying", " in", " the", " sky", ".", " Lily", "'s"], "acts": [0.0, 0.0, 0.0, 0.0, 0.0, 0.0, 0.0, 0.0, 0.0, 0.0, 0.0, 0.0, 0.0, 1.1987, 1.1896, 6.0759, 0.0, 0.0, 0.0, 0.0, 0.0, 0.0, 0.0, 0.0], "max_pos": 15, "max_act": 6.0742}]}